{
"uekjdf3wtywzuqjp57zvogce":["beafihn","Beatrice Fihn"],
"2rnfoifxtknpvymzg7lrrd4x":["elgandalf","elGandalf - Fihto - CosplayMages"],
"3po7r4nu55m2qkh2p2ddl6hf":["fatimafihri","Fatima Fihri"],
"wq2pb77joisn5aziw54dlifh":["fih","Filipe vai na THE ERAS TOUR - 25/11"],
"e4zw4byrk6a7niovariah2vp":"fihough",
"lmfc56bvnmsmmsojxcykq4f4":["fihu.omg.lol","fihu"],
"fdeqnk2ubygoxjpu7m2qjivm":["fiama","fih"],
"42iyafn4ijjksee27hmaknsk":"fihmunrunna",
"dpdywzim7b5k6siljz5grwt7":"fihella",
"bydrnyabpfhttnws3ywmu6nm":["fihyn","Fihyn"],
"xgvyd24jgbey7y5w55bqmovn":["hichamfassifihri","Hicham Fassi-Fihri"],
"2ah6vrwzqrt6xfeouvvh5o46":["willsbamboobike","Will Fihn Ramsay"],
"o7nvtfsavxu6apefqr3zlhi3":["mcpringle","Marcus Fihlon"]
}
