{
"b2dhqqufqgo6l2ll6zw54ucg":["abbyaffchen","Abby Äffchen"],
"45oc2wrsr6ocsn4xj3t3x6gh":["aloispluesch","Alois Äffchen"],
"o5agtgdnds4bcbgtjae23jih":["anguirel","Code-Äffchen"],
"i7fbuh7cjexyzdoicu36addc":["feinesstoeffchen","Kati Stöffchen"],
"bjv2mudpmql6wm7s5xqlk4rz":["ffchll","Maf"],
"7zhkhmdp5itmsbn5vcl5dbuq":["ffcdigao","Rodrigo Nogueira"],
"l2daiidjtvam3l2c7avw7hez":["ffcrls","Fernanda"],
"2ttyliyqfyglkyimyza7754l":"ffconnoisseur",
"3vlxv7zagsr2vzwgc5wk74hq":["ffcj","Dr. bear. nat."],
"upcywvw367sm5zw4svjzofc5":["ffc706","빡이"],
"i5b2kmy7kskmxh2z3pntezfq":["ffcc","피자쨩"],
"gbhqvg2onv3eltpxg2pindjq":["ffcubatl","Ffcubatl"],
"tpiqghlmba3wb4vnhqh7r474":["ffcowboymx","Lázaro Lorenzo"],
"zzezqikbxgrkin4ck4zcg2zr":"ffc0cb",
"hj5wvs3qu6nc246bhzi5u5he":["frivoleraffe","Frivoles Äffchen"],
"faztbdg62j5xdxfw2vewjszc":["steffcik","SteFFciK"],
"mpfv5aujldnzvwy5mhu6ykxw":["tylerffcreator","TylerFFCreator"]
}
