{
"taxctohjydf56ffldetzdae6":"5ftofamazing",
"tzki72vpxllqalj7pqi5zk25":["4ftoffluff","AwyaðŸ”ž"],
"q26kboa3q2ls24ti2ljwgmvt":"5ftoffun",
"5oaxblxlamr6r2zbscggaxos":["amanharan","amanharan || Ghost in the Ftog"],
"z2u2xaum46poarwwoqt5czjs":["ftoya108","è—¤è°·"],
"7zxpcqkjlzqbuochgp3bqeoc":"fton",
"xzol44uvzptfntzqestzc3yk":"ftoole",
"y7qc4p2rji2aqu3grga4dzzx":"ftominc",
"ez2pnou6iynqnbamqyac5cvs":["ftorresps","Fernando Torres "],
"woldb2w3dobfl45qr7zost2y":["ftorres","FTorres"],
"25wop6kpf2fl7kuyxtuqqt36":"ftoyama",
"o46eu3ndz2cbn4krarikgjbl":["ftomo","ãˆãµã¨ã‚‚"],
"l36c6to5exbxcrjhecabuirp":"ftom89",
"kcpuyvhs36g7g2cw5776mobp":["ftosse","ftosse"],
"qcyhjnfrbhycq6ldrkl7tgxh":"ftotheerdi",
"jtqpz5hauvq5txseabkujw6q":"ftodude",
"gjoz2iaauvganzqjvoz2rclo":["ftorche","Florencia Torche"],
"riydsdfr3loy4gnji7ni6da7":["jupiterwaff","Jupiter Wolfâ­ï¸FTO, Bewhiskered"],
"mtigx2ekeppwqroezp7c3ysm":["photodeer","Yiri ðŸ”œ FTO"],
"5to735n5opwthiuwk5rqmady":["tobidoge","ðŸŒ³ Tobi ðŸŒ·ðŸ• -> FTO"]
}
