{
"7jbv2z72tnpis324nsdp5q4u":["chicofajita","Chico Fajita"],
"ryfpz67uoeh2lgaynavspsvb":["cliffordfajardo","Clifford Fajardo"],
"rqrf2cw2v3ktshlk5cduezx5":["crispyfajita","CrispyFajita"],
"7jt4azkmlr3ecrpfgrirbl37":["ediblefromage","Jamie (Fajner)"],
"kq3ddo5p7pifn37yzgilj336":["fajarsiddiq.com","Fajar Siddiq"],
"no6n2udwmebwesgkdwc7t543":"fajita",
"ph2wix7qbnegl76anjikzfyh":["fajardo","forjado"],
"rurkejymlphu45zuzohroctv":["fajaryan","Fajar Riyan"],
"x4rspbi5cxkxcausabxe6irb":["fajarfebriansyah.com","Fajar Febriansyah"],
"cftpipzn6is5kffnzqqrx7me":["fajarmsdq","Fajarmsdq"],
"qwwvoscztubp6hdltugwu6g5":"fajar",
"kmhh6zlv7bigcflud262xve5":["fajar2","Fa"],
"tj4ocfq3vl7jyxcbeiwrtlyn":"fajarcipta",
"kqzehn4aoymr5jfbev6wt6gh":["fajitadoctor","Mark K"],
"gyndipjkstc6yk4ry5v4oxrm":["fajoba","Fajoba"],
"y74fp7ydtyyzki2ueggl3utf":"fajitas",
"76ok7thtgjanewvhzuv4pnmi":["fajny","Файний Шашличок"],
"sqeqzkh5k366rqf575ononij":["fajoho","Verbindungslehrer"],
"5kfpvs2fysi4tomnigrs2g2z":["fajer","فجر الخليفة"],
"jgah2o5lmqvoizqe27cefajb":["fajyobore","Fajyobore"],
"ku5mvqty7qvcpvz755qcslfz":["fajardojedi","Alejandro "],
"zrckwj3xgbojn6557uexojmb":"faj0000",
"bbvrpcbdzenz3ewmj6g7wo6r":["fajarariano","fajar arian o."],
"fo5qvsyrybptfxi6xvpuak6y":"fajulleiro",
"ucozibrh2wq6mhcd7isv4a7n":["fajri","Fajri"],
"ivzq4g6q5huudtjhsap632zm":["fkzamel","Fajer "],
"mh7qrikulvp6vjzd3imatfc7":["fuzyjoe","Jose Carlos Fajardo"],
"eokcjy37obzdsr6qoruwg323":["gabefajardo","Gabe Fajardo"],
"2ow5wioriqow3c2losmdiszd":["guillemclusella","Guillem Clusella i Fajarnés"],
"vveiy3o277mysunqnyiwqvli":["ibnufathoni","Ibnu Fathoni Fajaria Noor"],
"hsavyud6falxzghv3p7qmpse":["joanrabat","Joan Rabat Fajardo"],
"f3z5prcx5wmel5ilvm7d6u5w":["jufajardini","Juliana Fajardini"],
"ynju6o5myco6ayp6zpaubadu":["juliebf","Julie Fajgenbaum "],
"uwj3cg4lbytkc7ubkauju4e2":["kalefajita","Kale Fajita"],
"ny6hp65phhfwl4paxjmseal7":["kazuhacker","joao fajuto"],
"zdgu3kyngfiydszeb5k6tiam":["leberkaassemmi","René Fajs"],
"co5f3fdjzs3khbmhjhgmzjxl":["lisafajita","Lisa Fajita 🏳️‍⚧️🏳️‍🌈"],
"piebji6w656eyg6ezgtm67rn":["mariannefajstrup","Marianne Fajstrup"],
"nbn35iq5fkxxglsdqnuibzbr":["mibnufajar","Muhammad Ibnu Fajar"],
"olyjdjezbroklaw65fxbfee6":["muhfajar","Fajar"],
"3r3ugshmteaqwud25dvqkl6k":["nascararafat","PastaFajuulpods"],
"inegm7m62celmxy74dpee4zp":["petulf","Peťul Fajkusová"],
"khf54krqek6qmp6uzsks5jbk":["rafafajardo","Rafael Fajardo"],
"2w33ss5brj56zhcro735ihpk":["rafaelfajardo","Rafael Fajardo"],
"xdafmz2udanw72pntoc75adn":["rakafajrip","Raka Fajri"],
"plx5wfa2c3ykrrtiw7ycurmc":["shadyfajita","ShadyFajita"],
"fxmt2g22zgms4qqu4g4lsyo6":["wirlous","Carlos Fajardo"],
"bu3yhrumiylpnnnayexscijy":["xiecty","Faj"]
}
