{
"yudaqarbquqdtar6nq6exwnm":["alexanderfaolchu","Alexander Faolchu"],
"kkufpntufuwo5ihwwcnzh4ow":["amzuh","💉faolan"],
"6tcg4key3cfcvanrlt7hgdo2":["averil","Ave De Faoite"],
"5fts3teqwxf6kfyx3tglesuo":["beardjarin","Faolan"],
"7j6lz5s63czpnc7vbjrdpgza":["brujofaolan","Faolan"],
"gauave2tqumg2pnuclqpkz5c":["citruslupus","Faolan"],
"grrdh2mhpps4svgn7eez3h6z":["coyotepelts","🌿 Faolan"],
"m47fsat3ibfbyctbuz4vzkx5":["corvyfaolain","Corvus Faolain"],
"uykgld3hcx5kqqprk5n66qsz":["conroicht","Faoladh"],
"gwovfzd64boj7c2lho7g4cqx":["diede","Diede // Faolon 🐉"],
"2byrunnxyu5f3ntc3fekgka3":["faolrougelune","Faol Rougelune"],
"ko56fzxhx2gld64oafpidy6o":["faolancanidae","Faolán Canidae "],
"qfptiegqsouy7xbrr4pjxjix":["faoljew","Tullamore Jew"],
"wboqqhwb5iyn2epgvfqbpwra":["fao","Fao"],
"bc4fhozhcfqpwz33qwosve6j":["faouzi","Faouzi Taalba"],
"np5xvdcopba3yrs7e7snnaqc":["faoliveira","FA"],
"dty67hjwvp6id52ul7ev4kbv":["faolan","Faolan"],
"75hu76bi4igovlnmgaiydtdd":["faoldhia","Faol Dhia"],
"2or33mm3nf7fayt3qt5zpl2w":["fao89","Fabricio Aguiar"],
"okxoumjtgwp5yzvelghlgeg4":["faorynn","Faorynn"],
"dadmsoaomgxzytdbhbskbgiw":["faothechee","FaoTheChee"],
"apes2ez2ewqn3izjts7g6ecu":["faol","𝔉𝔞𝔬𝔩"],
"zsq2wqkx62qfrwjz5c26neqg":["faolan-art","✨ Faolán ✨ | Vtuber"],
"tdpzczwwkueag5oviyeq7mck":["faoitw","u."],
"t6ggjqznssrrmnmtnxvkyfic":["faolanaviternal","Faolan Aviternal"],
"2p2rjaiukorrt2xz7flcrkov":["faolanpanriel","Faolan"],
"xllvd5xha7joiq3dv4jy5ren":["faoxie","Faoxie"],
"3rw6kjsya5bpg5td77gh2664":["faolanwolfsavor","KageWolf"],
"gy7vcb3vl7dl4ft6ldgmspyi":["faoztas","Furkan Anıl Öztaş"],
"s3sdasufehv3wejjqcaqvvu3":["faofaou","faofaou"],
"64zapwagn7a37lxhe77sydb7":"faolanxfiltiarn5",
"3ke7igv3pn7ng3sr5v74cdaq":["faorameridian","Faora Meridian"],
"d4hyd27edvscsn6xi5abfvg2":["faota","faota"],
"ytzg3t2ketukk2cyvy4cxltj":"faoli",
"ev2mp7ai7bm4s2hwptvl6bua":"faoltiarna",
"4mhj3f5refr37ibwkvtxb6kh":["faolamb","Faolán"],
"yk4japdwf3ewj7ekcmguvooc":["faoladh","Poses a danger to themself and others"],
"lntkcss4sxafj7tc44wn7njn":["faolan2023","Faolan"],
"gs45je7kgnw4e2f4czehthso":"faoiltarna",
"ym3bpxdmiujg25matcctkdvh":"faolanxfiltiarn12",
"tjmfeagjh3tlt6ja3ygxi57b":"faoi",
"yzut55ub2e7vrzcgescwqrp2":"faolanxfiltiarn3",
"irys5fls527wbhtd666n4qhz":["faolivier","Françios Olivier"],
"rlc556yitrpcibltnpkjpbpx":"faottis",
"dp3z5frvpos2oplvw7wdmcqf":["fa0lan","@_Fao_lan_"],
"3fkrx2hlqf7reqnqaek5r4u5":["faowolf","faowolf00"],
"mqt7imujd3gracmsrfktcyae":["faowoo","fao"],
"opx2f665jaos574gpqviiwwm":"faolin30",
"5bxvr6whutdbjngoycuwt4fd":"faolane",
"xhc6qhkdzj2ii2w653qhiuk2":"faoria",
"orlnovbip3yztb6kxu7nzsac":["fgnactual","Eoin Ó Faodhagáin 🇵🇸"],
"zazxj5anjifn7w4sl5rvv7rt":["hannahwordpotions","Hannah Faoilean"],
"dzcffsng4p3rot5dnqruuhdk":["jazzyfaox","JazzyFaox"],
"tibzhbnpxxkbbn5bqpitzb52":["kalefaolan","Kale Sw Faolan"],
"5rdidlqyeosclkcuzevbkcnw":["koboldking","Faolan"],
"qccffbh2lukn24fol3dz6eiv":["leggyfao","Faolan"],
"fsdjsfjres223e556ds6tvtm":["mattvxwhelan","Matt Whelan / Mathúin Ó Faoláin"],
"2eaakv5cr5ab36dk2ymawhet":["marcdefaoite","Marc de Faoite "],
"wtcuvb7d73dkj5tndr7vvna6":["ofaolain","Críostóir Ó Faoláin"],
"e3qezzspgcvjpsmmrwwu2q4z":["pupfaolan","Pup Faolan"],
"7dzsowav4iqk6thfqg2o45ch":["seamasbelfast","Cllr. Séamas de Faoite"],
"z2dkgjqnm3mdaamm54q7cw5g":["sebfaron","Ducoup faon "],
"qqm2p3lfapnw4rsyg4y7ptdz":["shouldergeek","Jonathan Braman,  MD, MHA, FAOA"],
"nidfaqkfpcurgjycys4x2zah":["woofwitch","Faolann🐺🏳️‍⚧️🏳️‍🌈"],
"mivigdt7szsqiakg2enbdygf":["yourfavpup","Pup Faolán"]
}
