{
"s437beknmp65bo5jblizzoy6":["fdm2","fdm2"],
"6uca2liwb5xckjrk4x2pxo2o":"fdmnofs",
"oqefyfnonijpiov7jv4vjnsk":["fdms.eu","Florian Stöger"],
"tw33isqqmti4pylla773n5c7":["fdmafc","FullDeck & Missing a Few Cards"],
"gy2ilzidzpha4mq64ljkihae":"fdmts",
"k56vlhk46wb23t3iynlnn64q":["fdms","Florian Stöger // @fdms.eu on bsky! //"],
"awekwdq6x4ak2s362j735eau":"fdmskpop",
"dcovhlppojfpso7mjznbuyxh":"fdm",
"muqd5o75jnlthbztmowcww64":["fdmbxl","Frédéric De Muynck"],
"l7utw4w57xje7jhb5fbyxko4":["fdmajora","FDMajora"],
"n6ftnzoogueaedcopp5nkaoo":["fdminf","Flavio Medeiros"]
}
